Metadata-Version: 2.1
Name: mrfifo
Version: 0.7
Summary: Map-Reduce parallelism over FIFOs (named pipes)
Home-page: https://github.com/marvin-jens/mrfifo
Author: Marvin Jens
Author-email: marvin.jens@charite.de
License: MIT
Project-URL: Bug Tracker, https://github.com/marvin-jens/mrfifo/issues
Classifier: Programming Language :: Python :: 3
Classifier: License :: OSI Approved :: MIT License
Classifier: Operating System :: Unix
Requires-Python: >=3.10
License-File: LICENSE
Requires-Dist: setproctitle
Requires-Dist: isal
Requires-Dist: pandas
Provides-Extra: tests
Requires-Dist: pytest; extra == "tests"
Requires-Dist: pytest-cov; extra == "tests"
Requires-Dist: coverage; extra == "tests"
